dj_git-0.3.dist-info/DESCRIPTION.rst
dj_git-0.3.dist-info/METADATA
dj_git-0.3.dist-info/RECORD
dj_git-0.3.dist-info/WHEEL
dj_git-0.3.dist-info/metadata.json
dj_git-0.3.dist-info/top_level.txt
git/__init__.py
git/admin.py
git/apps.py
git/experimental.py
git/models.py
git/tests.py
git/urls.py
git/utils.py
git/views.py
git/management/__init__.py
git/management/__pycache__/__init__.cpython-35.pyc
git/management/commands/__init__.py
git/management/commands/_private.py
git/management/commands/format_readme.py
git/management/commands/updategitprojects.py
git/management/commands/__pycache__/__init__.cpython-35.pyc
git/management/commands/__pycache__/updategitprojects.cpython-35.pyc
git/migrations/0001_initial.py
git/migrations/0002_auto_20160519_1954.py
git/migrations/__init__.py
git/static/git/charts/commits_count_by_committer.svg
git/static/git/css/graph.css
git/static/git/css/normalize.css
git/static/git/css/skeleton.css
git/static/git/css/style.css
git/static/git/js/fancify.js
git/static/git/js/jquery.js
git/templates/404.html
git/templates/git/base.html
git/templates/git/commits_by_day.html
git/templates/git/detail.html
git/templates/git/index.html
git/templates/git/search_project.html
