Metadata-Version: 2.0
Name: dj-git
Version: 0.3
Summary: A simple Django app to manage your Git projects.
Home-page: https://github.com/TaurusOlson/django-git
Author: Taurus Olson
Author-email: taurusolson@gmail.com
License: MIT License
Keywords: django,application,git,projects
Platform: UNKNOWN
Classifier: Environment :: Web Environment
Classifier: Framework :: Django
Classifier: Framework :: Django :: 1.9
Classifier: Intended Audience :: Developers
Classifier: License :: OSI Approved :: MIT License
Classifier: Operating System :: OS Independent
Classifier: Programming Language :: Python
Classifier: Programming Language :: Python :: 3
Classifier: Programming Language :: Python :: 3.4
Classifier: Programming Language :: Python :: 3.5
Classifier: Topic :: Internet :: WWW/HTTP
Classifier: Topic :: Internet :: WWW/HTTP :: Dynamic Content
Requires-Dist: django
Requires-Dist: pygal
Requires-Dist: pygit2
Requires-Dist: pytz
